dfd/__init__.py
dfd/create.py
dfd/utils.py
dfd/dataset/__init__.py
dfd/dataset/analyses.py
dfd/datasheet/__init__.py
dfd/datasheet/layout.py
dfd/datasheet/structures.py
datasheet_for_dataset-0.0.1.dist-info/METADATA
datasheet_for_dataset-0.0.1.dist-info/WHEEL
datasheet_for_dataset-0.0.1.dist-info/licenses/LICENSE
datasheet_for_dataset-0.0.1.dist-info/RECORD
